CHANGELOG.txt
LICENCE.txt
MANIFEST.in
README.txt
setup.py
flask_mongo_crud/__init__.py
flask_mongo_crud/flask_mongo_crud.py
flask_mongo_crud/requirements.txt
flask_mongo_crud/utils.py
flask_mongo_crud.egg-info/PKG-INFO
flask_mongo_crud.egg-info/SOURCES.txt
flask_mongo_crud.egg-info/dependency_links.txt
flask_mongo_crud.egg-info/requires.txt
flask_mongo_crud.egg-info/top_level.txt